<?xml version="1.0" encoding="UTF-8"?>
<MetaDataObject xmlns="http://v8.1c.ru/8.3/MDClasses" xmlns:app="http://v8.1c.ru/8.2/managed-application/core" xmlns:cfg="http://v8.1c.ru/8.1/data/enterprise/current-config" xmlns:cmi="http://v8.1c.ru/8.2/managed-application/cmi" xmlns:ent="http://v8.1c.ru/8.1/data/enterprise" xmlns:lf="http://v8.1c.ru/8.2/managed-application/logform" xmlns:style="http://v8.1c.ru/8.1/data/ui/style" xmlns:sys="http://v8.1c.ru/8.1/data/ui/fonts/system" xmlns:v8="http://v8.1c.ru/8.1/data/core" xmlns:v8ui="http://v8.1c.ru/8.1/data/ui" xmlns:web="http://v8.1c.ru/8.1/data/ui/colors/web" xmlns:win="http://v8.1c.ru/8.1/data/ui/colors/windows" xmlns:xen="http://v8.1c.ru/8.3/xcf/enums" xmlns:xpr="http://v8.1c.ru/8.3/xcf/predef" xmlns:xr="http://v8.1c.ru/8.3/xcf/readable" xmlns:xs="http://www.w3.org/2001/XMLSchema" xmlns:xsi="http://www.w3.org/2001/XMLSchema-instance" version="2.9">
	<FilterCriterion uuid="c4b4e887-ae62-40ec-896c-156db2705711">
		<InternalInfo>
			<xr:GeneratedType name="FilterCriterionManager.СтруктураПодчиненности" category="Manager">
				<xr:TypeId>4ece4884-3370-4c00-9383-1b35bc723109</xr:TypeId>
				<xr:ValueId>ad500538-eb5e-4afb-8934-ebe4f6da1b06</xr:ValueId>
			</xr:GeneratedType>
			<xr:GeneratedType name="FilterCriterionList.СтруктураПодчиненности" category="List">
				<xr:TypeId>01f21d55-556b-4e51-be47-9279f4f451ba</xr:TypeId>
				<xr:ValueId>979d3669-77cb-4a98-9bd1-1e6a6f223f12</xr:ValueId>
			</xr:GeneratedType>
		</InternalInfo>
		<Properties>
			<Name>СтруктураПодчиненности</Name>
			<Synonym>
				<v8:item>
					<v8:lang>ru</v8:lang>
					<v8:content>Структура подчиненности</v8:content>
				</v8:item>
				<v8:item>
					<v8:lang>uk</v8:lang>
					<v8:content>Структура підпорядкованості</v8:content>
				</v8:item>
			</Synonym>
			<Comment/>
			<Type>
				<v8:TypeSet>cfg:DocumentRef</v8:TypeSet>
			</Type>
			<UseStandardCommands>true</UseStandardCommands>
			<Content>
				<xr:Item xsi:type="xr:MDObjectRef">Document.ВводСведенийОбУчетеЗаработкаРаботников.Attribute.ДокументОснование</xr:Item>
				<xr:Item xsi:type="xr:MDObjectRef">Document.ВводСведенийОбУчетеОсновногоЗаработкаРаботниковОрганизаций.Attribute.ОтражаемыйДокумент</xr:Item>
				<xr:Item xsi:type="xr:MDObjectRef">Document.ВводСведенийОбУчетеОсновногоЗаработкаРаботниковОрганизаций.TabularSection.РаботникиОрганизации.Attribute.УдалитьПриказ</xr:Item>
				<xr:Item xsi:type="xr:MDObjectRef">Document.ВводСведенийОПлановыхНачисленияхРаботниковОрганизаций.Attribute.ДокументОснование</xr:Item>
				<xr:Item xsi:type="xr:MDObjectRef">Document.ВводСведенийОПлановыхНачисленияхРаботниковОрганизаций.TabularSection.ОсновныеНачисления.Attribute.УдалитьПриказ</xr:Item>
				<xr:Item xsi:type="xr:MDObjectRef">Document.ВводСведенийОПлановыхНачисленияхРаботниковОрганизаций.TabularSection.УдалитьДополнительныеНачисления.Attribute.УдалитьПриказ</xr:Item>
				<xr:Item xsi:type="xr:MDObjectRef">Document.ВводСведенийОПлановыхНачисленияхУдержанияхРаботников.TabularSection.Удержания.Attribute.ДокументОснование</xr:Item>
				<xr:Item xsi:type="xr:MDObjectRef">Document.ВводСведенийОПлановыхУдержанияхРаботниковОрганизаций.TabularSection.Удержания.Attribute.ДокументОснование</xr:Item>
				<xr:Item xsi:type="xr:MDObjectRef">Document.ВозвратНаРаботуОрганизаций.TabularSection.РаботникиОрганизации.Attribute.УдалитьПриказ</xr:Item>
				<xr:Item xsi:type="xr:MDObjectRef">Document.ГрафикОтпусковОрганизаций.TabularSection.РаботникиОрганизации.Attribute.УдалитьПриказ</xr:Item>
				<xr:Item xsi:type="xr:MDObjectRef">Document.ЗаявлениеРасчетВФСС.TabularSection.ДокументыПоНачислениям.Attribute.Документ</xr:Item>
				<xr:Item xsi:type="xr:MDObjectRef">Document.ЗаявлениеРасчетВФСС.TabularSection.Больничные.Attribute.Документ</xr:Item>
				<xr:Item xsi:type="xr:MDObjectRef">Document.ЗаявлениеРасчетВФСС.TabularSection.Декретные.Attribute.Документ</xr:Item>
				<xr:Item xsi:type="xr:MDObjectRef">Document.ЗаявлениеРасчетВФСС.TabularSection.БольничныеНС.Attribute.Документ</xr:Item>
				<xr:Item xsi:type="xr:MDObjectRef">Document.ЗаявлениеРасчетВФСС.TabularSection.ПособияНаПогребение.Attribute.Документ</xr:Item>
				<xr:Item xsi:type="xr:MDObjectRef">Document.ИзменениеПараметровРасчетаИндексации.Attribute.ДокументОснование</xr:Item>
				<xr:Item xsi:type="xr:MDObjectRef">Document.ИзменениеПараметровРасчетаИндексацииПоДолжностям.Attribute.ДокументОснование</xr:Item>
				<xr:Item xsi:type="xr:MDObjectRef">Document.КадровоеПеремещениеОрганизаций.TabularSection.РаботникиОрганизации.Attribute.УдалитьПриказ</xr:Item>
				<xr:Item xsi:type="xr:MDObjectRef">Document.КадровоеПеремещениеОрганизаций.TabularSection.ОсновныеНачисления.Attribute.УдалитьПриказ</xr:Item>
				<xr:Item xsi:type="xr:MDObjectRef">Document.КадровоеПеремещениеОрганизаций.TabularSection.УдалитьДополнительныеНачисления.Attribute.УдалитьПриказ</xr:Item>
				<xr:Item xsi:type="xr:MDObjectRef">Document.КомандировкиОрганизаций.TabularSection.РаботникиОрганизации.Attribute.УдалитьПриказ</xr:Item>
				<xr:Item xsi:type="xr:MDObjectRef">Document.НачислениеЗарплатыРаботникам.TabularSection.ПогашениеЗаймов.Attribute.ДоговорЗайма</xr:Item>
				<xr:Item xsi:type="xr:MDObjectRef">Document.НачислениеЗарплатыРаботникамОрганизаций.TabularSection.Начисления.Attribute.УдалитьПриказ</xr:Item>
				<xr:Item xsi:type="xr:MDObjectRef">Document.НачислениеЗарплатыРаботникамОрганизаций.TabularSection.Удержания.Attribute.ДокументОснование</xr:Item>
				<xr:Item xsi:type="xr:MDObjectRef">Document.НачислениеЗарплатыРаботникамОрганизаций.TabularSection.ПогашениеЗаймов.Attribute.ДоговорЗайма</xr:Item>
				<xr:Item xsi:type="xr:MDObjectRef">Document.НачислениеЗарплатыРаботникамОрганизаций.TabularSection.УдалитьДополнительныеНачисления.Attribute.УдалитьПриказ</xr:Item>
				<xr:Item xsi:type="xr:MDObjectRef">Document.НачислениеОтпускаРаботникамОрганизаций.Attribute.ПриказОтпускОрганизации</xr:Item>
				<xr:Item xsi:type="xr:MDObjectRef">Document.НачислениеПоБольничномуЛисту.Attribute.ПервичныйБольничныйЛист</xr:Item>
				<xr:Item xsi:type="xr:MDObjectRef">Document.НачислениеПоБольничномуЛисту.Attribute.УдалитьПриказ</xr:Item>
				<xr:Item xsi:type="xr:MDObjectRef">Document.НачислениеПоБольничномуЛисту.TabularSection.Начисления.Attribute.УдалитьПриказ</xr:Item>
				<xr:Item xsi:type="xr:MDObjectRef">Document.НачислениеПоБольничномуЛисту.TabularSection.РасчетСреднего.Attribute.УдалитьПриказ</xr:Item>
				<xr:Item xsi:type="xr:MDObjectRef">Document.НевыходыВОрганизациях.Attribute.ДокументОснование</xr:Item>
				<xr:Item xsi:type="xr:MDObjectRef">Document.НевыходыВОрганизациях.TabularSection.Начисления.Attribute.УдалитьПриказ</xr:Item>
				<xr:Item xsi:type="xr:MDObjectRef">Document.ОплатаПоСреднемуЗаработку.Attribute.УдалитьПриказ</xr:Item>
				<xr:Item xsi:type="xr:MDObjectRef">Document.ОплатаПраздничныхИВыходныхДнейОрганизаций.TabularSection.Начисления.Attribute.УдалитьПриказ</xr:Item>
				<xr:Item xsi:type="xr:MDObjectRef">Document.ОплатаСверхурочныхЧасов.TabularSection.Начисления.Attribute.УдалитьПриказ</xr:Item>
				<xr:Item xsi:type="xr:MDObjectRef">Document.Опрос.Attribute.Рассылка</xr:Item>
				<xr:Item xsi:type="xr:MDObjectRef">Document.ОтпускаОрганизаций.TabularSection.РаботникиОрганизации.Attribute.УдалитьПриказ</xr:Item>
				<xr:Item xsi:type="xr:MDObjectRef">Document.ОтпускПоУходуЗаРебенком.Attribute.УдалитьПриказ</xr:Item>
				<xr:Item xsi:type="xr:MDObjectRef">Document.ОтпускПоУходуЗаРебенком.TabularSection.ПлановыеУдержания.Attribute.ДокументОснование</xr:Item>
				<xr:Item xsi:type="xr:MDObjectRef">Document.ОтражениеЗарплатыВРеглУчете.TabularSection.Начисления.Attribute.УдалитьПриказ</xr:Item>
				<xr:Item xsi:type="xr:MDObjectRef">Document.ОтражениеЗарплатыВРеглУчете.TabularSection.УдалитьДополнительныеНачисления.Attribute.УдалитьПриказ</xr:Item>
				<xr:Item xsi:type="xr:MDObjectRef">Document.ОтсутствиеНаРаботеОрганизаций.TabularSection.РаботникиОрганизации.Attribute.УдалитьПриказ</xr:Item>
				<xr:Item xsi:type="xr:MDObjectRef">Document.ПлатежноеПоручениеВходящее.TabularSection.Заявки.Attribute.ЗаявлениеРасчет</xr:Item>
				<xr:Item xsi:type="xr:MDObjectRef">Document.ПлатежноеПоручениеИсходящее.Attribute.ДокументОснование</xr:Item>
				<xr:Item xsi:type="xr:MDObjectRef">Document.ПлатежноеПоручениеИсходящее.TabularSection.ВыплатаЗаработнойПлаты.Attribute.Ведомость</xr:Item>
				<xr:Item xsi:type="xr:MDObjectRef">Document.ПлатежноеПоручениеИсходящее.TabularSection.ПеречислениеНалогов.Attribute.Ведомость</xr:Item>
				<xr:Item xsi:type="xr:MDObjectRef">Document.ПлатежныйОрдерСписаниеДенежныхСредств.TabularSection.ВыплатаЗаработнойПлаты.Attribute.Ведомость</xr:Item>
				<xr:Item xsi:type="xr:MDObjectRef">Document.ПремииРаботниковОрганизаций.Attribute.ДокументОснование</xr:Item>
				<xr:Item xsi:type="xr:MDObjectRef">Document.ПремииРаботниковОрганизаций.TabularSection.УдалитьДополнительныеНачисления.Attribute.УдалитьПриказ</xr:Item>
				<xr:Item xsi:type="xr:MDObjectRef">Document.ПриемНаРаботуВОрганизацию.TabularSection.РаботникиОрганизации.Attribute.ТрудовойДоговор</xr:Item>
				<xr:Item xsi:type="xr:MDObjectRef">Document.ПрохождениеКурсаОбучения.Attribute.ДокументУчастияВМероприятии</xr:Item>
				<xr:Item xsi:type="xr:MDObjectRef">Document.РасходныйКассовыйОрдер.Attribute.ДокументОснование</xr:Item>
				<xr:Item xsi:type="xr:MDObjectRef">Document.РасходныйКассовыйОрдер.TabularSection.ВыплатаЗаработнойПлаты.Attribute.Ведомость</xr:Item>
				<xr:Item xsi:type="xr:MDObjectRef">Document.РасчетПриУвольненииРаботникаОрганизаций.Attribute.ДокументОснование</xr:Item>
				<xr:Item xsi:type="xr:MDObjectRef">Document.РасчетПриУвольненииРаботникаОрганизаций.Attribute.УдалитьПриказ</xr:Item>
				<xr:Item xsi:type="xr:MDObjectRef">Document.РасчетСпецстажаРаботниковОрганизаций.TabularSection.Спецстаж.Attribute.Приказ</xr:Item>
				<xr:Item xsi:type="xr:MDObjectRef">Document.РегистрацияПростоевВОрганизациях.Attribute.УдалитьПриказ</xr:Item>
				<xr:Item xsi:type="xr:MDObjectRef">Document.РегистрацияРазовыхНачисленийРаботниковОрганизаций.Attribute.ДокументОснование</xr:Item>
				<xr:Item xsi:type="xr:MDObjectRef">Document.РегистрацияРазовыхНачисленийРаботниковОрганизаций.TabularSection.УдалитьДополнительныеНачисления.Attribute.УдалитьПриказ</xr:Item>
				<xr:Item xsi:type="xr:MDObjectRef">Document.РегистрацияРазовыхУдержанийРаботниковОрганизаций.Attribute.ДокументОснование</xr:Item>
				<xr:Item xsi:type="xr:MDObjectRef">Document.СдельныйНаряд.TabularSection.Исполнители.Attribute.УдалитьПриказ</xr:Item>
				<xr:Item xsi:type="xr:MDObjectRef">Document.Событие.Attribute.Основание</xr:Item>
				<xr:Item xsi:type="xr:MDObjectRef">Document.УвольнениеИзОрганизаций.TabularSection.РаботникиОрганизации.Attribute.УдалитьПриказ</xr:Item>
				<xr:Item xsi:type="xr:MDObjectRef">Document.УдалитьРегистрацияСобеседованияКандидата.Attribute.Основание</xr:Item>
				<xr:Item xsi:type="xr:MDObjectRef">Document.ПодтверждениеВыплатФСС.Attribute.ЗаявлениеРасчет</xr:Item>
			</Content>
			<DefaultForm>FilterCriterion.СтруктураПодчиненности.Form.ФормаСписка</DefaultForm>
			<AuxiliaryForm/>
			<ListPresentation/>
			<ExtendedListPresentation/>
			<Explanation/>
		</Properties>
		<ChildObjects>
			<Form>ФормаСписка</Form>
		</ChildObjects>
	</FilterCriterion>
</MetaDataObject>